plaidml/__init__.py
plaidml/boost-LICENSE
plaidml/context.py
plaidml/easylogging-LICENSE
plaidml/exceptions.py
plaidml/gmock-LICENSE
plaidml/half-LICENSE
plaidml/jsoncpp-LICENSE
plaidml/library.py
plaidml/llvm-LICENSE
plaidml/minizip-LICENSE
plaidml/op.py
plaidml/plaidml_setup.py
plaidml/protobuf-LICENSE
plaidml/settings.py
plaidml/six-LICENSE
plaidml/tile.py
plaidml-0.6.4.data/data/bin/pmlc
plaidml-0.6.4.data/data/include/half.hpp
plaidml-0.6.4.data/data/include/plaidml/plaidml++.h
plaidml-0.6.4.data/data/include/plaidml/plaidml.h
plaidml-0.6.4.data/data/include/plaidml/base/base.h
plaidml-0.6.4.data/data/include/plaidml/base/base_cpp.h
plaidml-0.6.4.data/data/lib/libplaidml.so
plaidml-0.6.4.data/data/share/plaidml/config.json
plaidml-0.6.4.data/data/share/plaidml/experimental.json
plaidml-0.6.4.data/data/share/plaidml/plaidml-config.cmake
plaidml-0.6.4.dist-info/METADATA
plaidml-0.6.4.dist-info/WHEEL
plaidml-0.6.4.dist-info/entry_points.txt
plaidml-0.6.4.dist-info/top_level.txt
plaidml-0.6.4.dist-info/RECORD
